api_buddy/__init__.py
api_buddy/cli.py
api_buddy/config/__init__.py
api_buddy/config/help.py
api_buddy/config/options.py
api_buddy/config/preferences.py
api_buddy/config/themes.py
api_buddy/config/variables.py
api_buddy/network/__init__.py
api_buddy/network/auth/__init__.py
api_buddy/network/auth/oauth2.py
api_buddy/network/request.py
api_buddy/network/response.py
api_buddy/network/session.py
api_buddy/utils/__init__.py
api_buddy/utils/auth.py
api_buddy/utils/exceptions.py
api_buddy/utils/formatting.py
api_buddy/utils/http.py
api_buddy/utils/spin.py
api_buddy/utils/typing.py
api_buddy/validation/__init__.py
api_buddy/validation/options.py
api_buddy/validation/preferences.py
api_buddy-1.0.1.dist-info/LICENSE
api_buddy-1.0.1.dist-info/METADATA
api_buddy-1.0.1.dist-info/WHEEL
api_buddy-1.0.1.dist-info/entry_points.txt
api_buddy-1.0.1.dist-info/RECORD
