Metadata-Version: 2.3
Name: api-buddy
Version: 1.0.1
Summary: The most pleasant HTTP API CLI tool
Home-page: https://github.com/fonsecapeter/api-buddy
License: MIT
Keywords: api_buddy,api-buddy,api,apibuddy,cli,cool,http,json,oauth2,requests,terminal,tool
Author: Peter Fonseca
Author-email: peter.nfonseca@gmail.com
Requires-Python: ~= 3.13.1
Classifier: Development Status :: 5 - Production/Stable
Classifier: Environment :: Console
Classifier: Intended Audience :: Developers
Classifier: License :: OSI Approved :: MIT License
Classifier: Operating System :: OS Independent
Classifier: Topic :: Internet :: WWW/HTTP
Classifier: Programming Language :: Python :: 3
Classifier: Programming Language :: Python :: 3.13
Requires-Dist: PyYAML (>=6.0.2,<6.1.0)
Requires-Dist: Pygments (>=2.19.1,<2.20.0)
Requires-Dist: beautifulsoup4 (>=4.7.1,<4.8.0)
Requires-Dist: colorama (>=0.4.6,<0.5.0)
Requires-Dist: docopt (>=0.6.2,<0.7.0)
Requires-Dist: mypy-extensions (>=1.0.0,<2.0.0)
Requires-Dist: requests-oauthlib (>=2.0.0,<2.1.0)
Requires-Dist: schema (>=0.6.8,<0.7.0)
Requires-Dist: yaspin (>=0.14.1,<0.15.0)
Project-URL: Documentation, https://poetry.eustace.io/docs
Project-URL: Repository, https://github.com/fonsecapeter/api-buddy
